nada_test/__init__.py
nada_test/cli.py
nada_test-0.6.0.dist-info/METADATA
nada_test-0.6.0.dist-info/WHEEL
nada_test-0.6.0.dist-info/entry_points.txt
nada_test-0.6.0.dist-info/top_level.txt
nada_test-0.6.0.dist-info/RECORD
