Metadata-Version: 2.1
Name: nada-test
Version: 0.6.0
Summary: Nillion Nada Test Framework
Classifier: License :: OSI Approved :: Apache Software License
Requires-Python: >=3.10
Provides-Extra: lint
Requires-Dist: pylint <3.3,>=2.17 ; extra == 'lint'
